flexclash/__init__.py
flexclash/data/__init__.py
flexclash/data/dataset.py
flexclash/data/poisoning_decorators.py
flexclash/model/__init__.py
flexclash/model/poisoning_decorators.py
flexclash/pool/__init__.py
flexclash/pool/defences.py
flexclash-0.0.3.dist-info/LICENSE.txt
flexclash-0.0.3.dist-info/METADATA
flexclash-0.0.3.dist-info/WHEEL
flexclash-0.0.3.dist-info/top_level.txt
flexclash-0.0.3.dist-info/RECORD
