Metadata-Version: 2.1
Name: flexclash
Version: 0.0.3
Author: Nuria Rodríguez Barroso
Keywords: adversarial attacks defences FL federated-learning flexible
License-File: LICENSE.txt
Requires-Dist: flexible-fl
